collective.explicitacquisition-2.0-py3.7-nspkg.pth
collective/explicitacquisition/__init__.py
collective/explicitacquisition/configure.zcml
collective/explicitacquisition/events.py
collective/explicitacquisition/interfaces.py
collective/explicitacquisition/testing.py
collective/explicitacquisition/tests/__init__.py
collective/explicitacquisition/tests/test_bad_acquisition.py
collective.explicitacquisition-2.0.dist-info/METADATA
collective.explicitacquisition-2.0.dist-info/WHEEL
collective.explicitacquisition-2.0.dist-info/namespace_packages.txt
collective.explicitacquisition-2.0.dist-info/top_level.txt
collective.explicitacquisition-2.0.dist-info/RECORD
